aeon4py/__init__.py
aeon4py/abstraction/__init__.py
aeon4py/abstraction/models/__init__.py
aeon4py/abstraction/models/button.py
aeon4py/abstraction/models/label.py
aeon4py/abstraction/models/textbox.py
aeon4py/abstraction/models/web_element.py
aeon4py/abstraction/product/__init__.py
aeon4py/abstraction/product/browser.py
aeon4py/abstraction/product/web_product.py
aeon4py/abstraction/selectors/__init__.py
aeon4py/abstraction/selectors/by.py
aeon4py/lib/aeon.extensions.log4j2.jar
aeon4py/lib/aeon.extensions.reporting.jar
aeon4py/lib/aeon.platform.python.jar
aeon4py/lib/aeon.selenium.jar
aeon4py/lib/log4j-api.jar
aeon4py/lib/log4j-core.jar
aeon4py/lib/log4j-slf4j-impl.jar
aeon4py/lib/lib/macos/chromedriver
aeon4py/lib/lib/macos/geckodriver
aeon4py/lib/lib/macos/operadriver
aeon4py/lib/lib/windows/IEDriverServer.exe
aeon4py/lib/lib/windows/MicrosoftWebDriver.exe
aeon4py/lib/lib/windows/chromedriver.exe
aeon4py/lib/lib/windows/geckodriver.exe
aeon4py/lib/lib/windows/operadriver.exe
aeon4py/sessions/__init__.py
aeon4py/sessions/java_session_adapter.py
aeon4py/sessions/java_session_factory_adapter.py
aeon4py/test_execution/__init__.py
aeon4py/test_execution/aeon_test_execution.py
aeon4py-0.0.3.dist-info/DESCRIPTION.rst
aeon4py-0.0.3.dist-info/METADATA
aeon4py-0.0.3.dist-info/RECORD
aeon4py-0.0.3.dist-info/WHEEL
aeon4py-0.0.3.dist-info/metadata.json
aeon4py-0.0.3.dist-info/top_level.txt
